wronnay_search_lib/__init__.py
wronnay_search_lib/controller.py
wronnay_search_lib/crawler.py
wronnay_search_lib/settings.py
wronnay_search_lib/warehouse.py
wronnay_search_lib-1.0.2.dist-info/LICENSE
wronnay_search_lib-1.0.2.dist-info/METADATA
wronnay_search_lib-1.0.2.dist-info/WHEEL
wronnay_search_lib-1.0.2.dist-info/top_level.txt
wronnay_search_lib-1.0.2.dist-info/RECORD
