Metadata-Version: 2.1
Name: wronnay_search_lib
Version: 1.0.2
Summary: A library of classes which can be used to build a search engine.
Home-page: https://github.com/Wronnay/search-lib
Author: Christoph Miksche
License: GPLv3
Keywords: wronnay,search,lib,crawler
Classifier: Programming Language :: Python :: 3
Classifier: License :: OSI Approved :: GNU General Public License v3 or later (GPLv3+)
Classifier: Operating System :: Unix
License-File: LICENSE
Requires-Dist: beautifulsoup4
Requires-Dist: lxml
Requires-Dist: mongoengine
